setup.py
mexbt_transfer_api/__init__.py
mexbt_transfer_api/transfer_api.py
mexbt_transfer_api.egg-info/PKG-INFO
mexbt_transfer_api.egg-info/SOURCES.txt
mexbt_transfer_api.egg-info/dependency_links.txt
mexbt_transfer_api.egg-info/not-zip-safe
mexbt_transfer_api.egg-info/requires.txt
mexbt_transfer_api.egg-info/top_level.txt