Metadata-Version: 1.0
Name: mexbt-transfer-api
Version: 0.1
Summary: A lightweight python client for the meXBT Transfer API
Home-page: http://github.com/meXBT/transfer-api-python
Author: meXBT
Author-email: william@mexbt.com
License: MIT
Platform: UNKNOWN
